pysentio_pkg/__init__.py
pysentio_pkg_astrandb-0.0.1.dist-info/DESCRIPTION.rst
pysentio_pkg_astrandb-0.0.1.dist-info/METADATA
pysentio_pkg_astrandb-0.0.1.dist-info/RECORD
pysentio_pkg_astrandb-0.0.1.dist-info/WHEEL
pysentio_pkg_astrandb-0.0.1.dist-info/metadata.json
pysentio_pkg_astrandb-0.0.1.dist-info/top_level.txt
