Metadata-Version: 2.0
Name: pysentio-pkg-astrandb
Version: 0.0.1
Summary: Python library for Sentio Pro Sauna Controller
Home-page: https://github.com/astrandb/pysentio
Author: Ake Strandberg
Author-email: ake@strandberg.eu
License: UNKNOWN
Platform: UNKNOWN
Classifier: Programming Language :: Python :: 3
Classifier: License :: OSI Approved :: MIT License
Classifier: Operating System :: OS Independent
Requires-Python: >=3.6
